aioayla/__init__.py
aioayla/const.py
aioayla-1.0.1.dist-info/METADATA
aioayla-1.0.1.dist-info/WHEEL
aioayla-1.0.1.dist-info/top_level.txt
aioayla-1.0.1.dist-info/RECORD
