Metadata-Version: 2.1
Name: aioayla
Version: 1.0.1
Summary: Interact with the Ayla IoT Platform
Home-page: https://github.com/dcmeglio/aioayla
Author: Dominick Meglio
Author-email: dmeglio@gmail.com
License: MIT
Keywords: ayla
Requires-Dist: httpx
